alu/vsrc/Adder.v
module Adder #(parameter LEN)
(
  input [LEN - 1:0] A
  input [LEN - 1:0] B
  input cin
  output [LEN - 1:0] out, 
  output cout
);

  assign {cout, out} = A + B + cin;

endmodule

alu/vsrc/alu.v
module ALU #(parameter LEN = 32)
(
  input [LEN - 1:0] A,
  input [LEN - 1:0] B,
  input [3:0] op,
  output Carry,
  output Zero,
  output Overflow,
  output reg [LEN - 1:0] Result
);

  wire cin, cout;
  wire [LEN - 1: 0] in_A, in_B, out;


  // when A-B or compare A & B, do A sub B
  assign cin = (~op[3] & ~op[2] & ~op[1] & op[0]) | (~op[3] & op[2] & op[1] & ~op[0]);
  assign in_A = A;
  assign in_B = {LEN{cin}} ^ B;
  Adder #(LEN) adder(.A(in_A), .B(in_B), .cin(cin), .out(out), .cout(cout));

  assign Carry = cout ^ cin;
  assign Zero = ~(|out);
  assign Overflow = ~(in_A[LEN - 1] ^ in_B[LEN - 1]) & (out[LEN - 1] ^ in_A[LEN - 1]);

  always @(*) begin
    case (op)
      4'b0000: Result = out;
      4'b0001: Result = out;
      4'b0010: Result = ~A;
      4'b0011: Result = A & B;
      4'b0100: Result = A | B;
      4'b0101: Result = A ^ B;
      4'b0110: Result = {{LEN - 1{1'b0}}, out[LEN-1]};
      4'b0111: Result = {31'b0, Zero};
      default: Result = 32'b0;
    endcase
  end

endmodule

alu/waveform.vcd
$version Generated by VerilatedVcd $end
$timescale 1ps $end

 $scope module TOP $end
  $var wire 32 & A [31:0] $end
  $var wire 32 ' B [31:0] $end
  $var wire  1 ) Carry $end
  $var wire  1 + Overflow $end
  $var wire 32 , Result [31:0] $end
  $var wire  1 * Zero $end
  $var wire  4 ( op [3:0] $end
  $scope module ALU $end
   $var wire 32 & A [31:0] $end
   $var wire 32 ' B [31:0] $end
   $var wire  1 ) Carry $end
   $var wire 32 . LEN [31:0] $end
   $var wire  1 + Overflow $end
   $var wire 32 , Result [31:0] $end
   $var wire  1 * Zero $end
   $var wire  1 # cin $end
   $var wire  1 - cout $end
   $var wire 32 & in_A [31:0] $end
   $var wire 32 $ in_B [31:0] $end
   $var wire  4 ( op [3:0] $end
   $var wire 32 % out [31:0] $end
   $scope module adder $end
    $var wire 32 & A [31:0] $end
    $var wire 32 $ B [31:0] $end
    $var wire 32 . LEN [31:0] $end
    $var wire  1 # cin $end
    $var wire  1 - cout $end
    $var wire 32 % out [31:0] $end
   $upscope $end
  $upscope $end
 $upscope $end
$enddefinitions $end


#0
0#
b00000000000000000000000000000000 $
b00000000000000000000000000000000 %
b00101010110011001001001000111110 &
b01110111110010110100000100100110 '
b0111 (
0)
1*
0+
b00000000000000000000000000000000 ,
0-
b00000000000000000000000000100000 .
#1
b01110111110010110100000100100110 $
b10100010100101111101001101100100 %
b00110110011101100011010011100001 &
b00100001101000111100000011000000 '
b0011 (
0*
1+
#2
b00100001101000111100000011000000 $
b01011000000110011111010110100001 %
b00000111000000101011011011101000 &
b00001001010011000001101010001101 '
b0111 (
0+
b00100000001000100000000011000000 ,
#3
b00001001010011000001101010001101 $
b00010000010011101101000101110101 %
b01011111001000011001010110110011 &
b00011111110001000011101111100010 '
b0011 (
b00000000000000000000000000000000 ,
#4
b00011111110001000011101111100010 $
b01111110111001011101000110010101 %
b01001010100100001010010001101000 &
b00000110010100010110001010000011 '
b0110 (
b00011111000000000001000110100010 ,
#5
1#
b11111001101011101001110101111100 $
b01000100001111110100000111100101 %
b01110100011111111000000100010001 &
b00000111101011000100011001000000 '
b0100 (
b00000000000000000000000000000000 ,
1-
#6
0#
b00000111101011000100011001000000 $
b01111100001010111100011101010001 %
b01011101101000000100001101101110 &
b01000001110111111100001011010110 '
b0111 (
b01110111111111111100011101010001 ,
0-
#7
b01000001110111111100001011010110 $
b10011111100000000000011001000100 %
b01110111000001110100001010001001 &
b01000011101111010101110001001110 '
b0110 (
1+
b00000000000000000000000000000000 ,
#8
1#
b10111100010000101010001110110001 $
b00110011010010011110011000111011 %
b00110001110000110010110111011011 &
b01011111101100100101101101000010 '
b0100 (
0+
#9
0#
b01011111101100100101101101000010 $
b10010001011101011000100100011101 %
b01011000010011011011011001001000 &
b00011110111101101001101100011100 '
b0101 (
1+
b01111111111100110111111111011011 ,
#10
b00011110111101101001101100011100 $
b01110111010001000101000101100100 %
b01110000111100111001111001000111 &
b01001001110000110010110101011010 '
b0000 (
0+
b01000110101110110010110101010100 ,
#11
b01001001110000110010110101011010 $
b10111010101101101100101110100001 %
b01100011010011101000000111100010 &
b00000000001110010110001000111100 '
b0110 (
1+
b10111010101101101100101110100001 ,
#12
1#
b11111111110001101001110111000011 $
b01100011000101010001111110100110 %
b00110101000101011011010100001010 &
b00000111001111000001100100100100 '
0+
b00000000000000000000000000000000 ,
1-
#13
b11111000110000111110011011011011 $
b00101101110110011001101111100110 %
b00100111001110001110100100111101 &
b01100110010111011010111011010111 '
b0100 (
#14
0#
b01100110010111011010111011010111 $
b10001101100101101001100000010100 %
b01011001111010111010111111100011 &
b00110000111011100101001100111111 '
b0110 (
1+
b01100111011111011110111111111111 ,
0-
#15
1#
b11001111000100011010110011000000 $
b00101000111111010101110010100100 %
b01010010011110110010110011011111 &
b00100101011011011101010001010000 '
b0001 (
0+
b00000000000000000000000000000000 ,
1-
#16
b11011010100100100010101110101111 $
b00101101000011010101100010001111 %
b00111001001010101011111100011110 &
b00000011000011100001011110111110 '
b0010 (
b00101101000011010101100010001111 ,
#17
0#
b00000011000011100001011110111110 $
b00111100001110001101011011011100 %
b01011100001011010100110111001101 &
b01111010000101010101101001000111 '
b0000 (
b11000110110101010100000011100001 ,
0-
#18
b01111010000101010101101001000111 $
b11010110010000101010100000010100 %
b00010010110111011101000110010001 &
b00101011110110001000100000100011 '
b0110 (
1+
b11010110010000101010100000010100 ,
#19
1#
b11010100001001110111011111011100 $
b11100111000001010100100101101110 %
b01001001111010100110100001110110 &
b00000100001001100011111001101011 '
b0000 (
1)
0+
b00000000000000000000000000000001 ,
1-
#20
0#
b00000100001001100011111001101011 $
b01001110000100001010011011100001 %
b01110000000110000101101101111110 &
b01110101000110011101110010110011 '
b0101 (
0)
b01001110000100001010011011100001 ,
0-
#21
b01110101000110011101110010110011 $
b11100101001100100011100000110001 %
b00001110000100011000111110101101 &
b01011000011010000101111010010101 '
b0111 (
1+
b00000101000000011000011111001101 ,
#22
b01011000011010000101111010010101 $
b01100110011110011110111001000010 %
b01001101101011101000010010011011 &
b00001101011111100001001110011111 '
b0011 (
0+
b00000000000000000000000000000000 ,
#23
b00001101011111100001001110011111 $
b01011011001011001001100000111010 %
b00010110100101111001010000010111 &
b00110100101101101111110011011101 '
b0111 (
b00001101001011100000000010011011 ,
#24
b00110100101101101111110011011101 $
b01001011010011101001000011110100 %
b01111111010001001101111101110101 &
b00001110101000101010110011000000 '
b0110 (
b00000000000000000000000000000000 ,
#25
1#
b11110001010111010101001100111111 $
b01110000101000100011001010110101 %
b01101110010000111000110101010111 &
b01100001000111011101100110100000 '
b0101 (
1-
#26
0#
b01100001000111011101100110100000 $
b11001111011000010110011011110111 %
b01100100111011101000000101111001 &
b00011010010010001001100010111110 '
b0110 (
1+
b00001111010111100101010011110111 ,
0-
#27
1#
b11100101101101110110011101000001 $
b01001010101001011110100010111011 %
b00011101011110010011100001110001 &
b01110110011101011110011010001011 '
b0100 (
0+
b00000000000000000000000000000000 ,
1-
#28
0#
b01110110011101011110011010001011 $
b10010011111011110001111011111100 %
b00011001110000010100101110111000 &
b00001001010100111011100000011100 '
1+
b01111111011111011111111011111011 ,
0-
#29
b00001001010100111011100000011100 $
b00100011000101010000001111010100 %
b01110101101110111011101001000000 &
b01010011001111100010000010010010 '
b0111 (
0+
b00011001110100111111101110111100 ,
#30
b01010011001111100010000010010010 $
b11001000111110011101101011010010 %
b01110000101011001100001111100101 &
b01000011010101100111110000010001 '
b0010 (
1+
b00000000000000000000000000000000 ,
#31
b01000011010101100111110000010001 $
b10110100000000110011111111110110 %
b00110101011000001111101011100101 &
b01010001011010000000101110111110 '
b0101 (
b10001111010100110011110000011010 ,
#32
b01010001011010000000101110111110 $
b10000110110010010000011010100011 %
b01111010010011101001010000100000 &
b00011111000101101001000001011001 '
b0011 (
b01100100000010001111000101011011 ,
#33
b00011111000101101001000001011001 $
b10011001011001010010010001111001 %
b01000110011110000100011010000000 &
b00110101101011100010010001110001 '
b0010 (
b00011010000001101001000000000000 ,
#34
b00110101101011100010010001110001 $
b01111100001001100110101011110001 %
b01111000111111111010011110110110 &
b00110100111100110000001111100110 '
b0111 (
0+
b10111001100001111011100101111111 ,
#35
b00110100111100110000001111100110 $
b10101101111100101010101110011100 %
b01011100011101010101110000101100 &
b00100011001101101001000100111101 '
b0000 (
1+
b00000000000000000000000000000000 ,
#36
b00100011001101101001000100111101 $
b01111111101010111110110101101001 %
b01100101010110001110010011110010 &
b00001000001001010001001010110110 '
0+
b01111111101010111110110101101001 ,
#37
b00001000001001010001001010110110 $
b01101101011111011111011110101000 %
b01110001010010101000010101110110 &
b00100101100111100100101100101000 '
b0110 (
b01101101011111011111011110101000 ,
#38
1#
b11011010011000011011010011010111 $
b01001011101011000011101001001110 %
b01110111010100011000000001000010 &
b00111111010111111001011011100000 '
b0010 (
b00000000000000000000000000000000 ,
1-
#39
0#
b00111111010111111001011011100000 $
b10110110101100010001011100100010 %
b00101001001100010000001100110001 &
b00110101000110110101000100100000 '
b0110 (
1+
b10001000101011100111111110111101 ,
0-
#40
1#
b11001010111001001010111011011111 $
b11110100000101011011001000010001 %
b01011111001101101100010010001100 &
b00100101110010000001010100000110 '
b0001 (
1)
0+
b00000000000000000000000000000001 ,
1-
#41
b11011010001101111110101011111001 $
b00111001011011101010111110000110 %
b00001010010101100110001010011001 &
b01011011001010010000111111101011 '
b0010 (
0)
b00111001011011101010111110000110 ,
0-
#42
0#
b01011011001010010000111111101011 $
b01100101011111110111001010000100 %
b00001101110111100101111100111100 &
b01010101011101111010010000001011 '
b0000 (
b11110101101010011001110101100110 ,
#43
b01010101011101111010010000001011 $
b01100011010101100000001101000111 %
b00011110111001000110111101111111 &
b00011011111011111110101010001011 '
b0001 (
b01100011010101100000001101000111 ,
#44
1#
b11100100000100000001010101110100 $
b00000010111101001000010011110100 %
b01100100101000010111110010011110 &
b00010100111011111001001001000010 '
b0010 (
b00000010111101001000010011110100 ,
1-
#45
0#
b00010100111011111001001001000010 $
b01111001100100010000111011100000 %
b00111001000000010011011001111110 &
b01110001011001001110111001101110 '
b0001 (
b10011011010111101000001101100001 ,
0-
#46
1#
b10001110100110110001000110010001 $
b11000111100111000100100000010000 %
b01101110011111101100100111111110 &
b01010110101111011101001101100000 '
b0110 (
1)
b11000111100111000100100000010000 ,
#47
b10101001010000100010110010011111 $
b00010111110000001111011010011110 %
b00111110010001001111011000111101 &
b01001000000010000101100011010110 '
b0101 (
0)
b00000000000000000000000000000000 ,
#48
0#
b01001000000010000101100011010110 $
b10000110010011010100111100010011 %
b00000100100000010000100100000111 &
b00111111010110011101100100011001 '
1+
b01110110010011001010111011101011 ,
#49
b00111111010110011101100100011001 $
b01000011110110101110001000100000 %
b01010100000100001101001111101101 &
b01101000100010101101110001001010 '
0+
b00111011110110001101000000011110 ,
#50
b01101000100010101101110001001010 $
b10111100100110111011000000110111 %
b01110110110111101011111101100110 &
b01000111110000011010000011010110 '
1+
b00111100100110100000111110100111 ,
#51
b01000111110000011010000011010110 $
b10111110101000000110000000111100 %
b01011101000000110010011011110000 &
b01010010000110000000001101110000 '
b0011 (
b00110001000111110001111110110000 ,
#52
b01010010000110000000001101110000 $
b10101111000110110010101001100000 %
b00010100100011111001101000111000 &
b01011111111101100110001010101100 '
b0110 (
b01010000000000000000001001110000 ,
#53
1#
b10100000000010011001110101010011 $
b10110100100110010011011110001100 %
b01101011001100101001110111011010 &
b01111110110110101101001000101011 '
b0010 (
1)
0+
b00000000000000000000000000000001 ,
1-
#54
0#
b01111110110110101101001000101011 $
b11101010000011010111000000000101 %
b01110111100000111100010111101100 &
b01100011011111000100111011001010 '
b0101 (
0)
1+
b10010100110011010110001000100101 ,
0-
#55
b01100011011111000100111011001010 $
b11011011000000000001010010110110 %
b00111000110001111111000111100101 &
b00011100011111011000010101001000 '
b0111 (
b00010100111111111000101100100110 ,
#56
b00011100011111011000010101001000 $
b01010101010001010111011100101101 %
b00011101010000101010111100011100 &
b00001010111111000100111101000111 '
b0101 (
0+
b00000000000000000000000000000000 ,
#57
b00001010111111000100111101000111 $
b00101000001111101111111001100011 %
b00001001111000100111111100001001 &
b01001001010000010100010110000100 '
b00010111101111101110000001011011 ,
#58
b01001001010000010100010110000100 $
b01010011001000111100010010001101 %
b00011100001000001001101000011110 &
b01001101110000100100111010001011 '
b0100 (
b01000000101000110011101010001101 ,
#59
b01001101110000100100111010001011 $
b01101001111000101110100010101001 %
b01101101101111100100110000010011 &
b00100001110100110010001001111000 '
b0101 (
b01011101111000101101111010011111 ,
#60
b00100001110100110010001001111000 $
b10001111100100010110111010001011 %
b01110100011101110100111100101000 &
b00011000101100011110000111011111 '
b0111 (
1+
b01001100011011010110111001101011 ,
#61
b00011000101100011110000111011111 $
b10001101001010010011000100000111 %
b00100000111110000110011101000100 &
b01110101101101010000100011001111 '
b0110 (
b00000000000000000000000000000000 ,
#62
1#
b10001010010010101111011100110000 $
b10101011010000110101111001110101 %
b00101000101000101000111101001010 &
b00001010010001001010001100001000 '
1)
0+
b00000000000000000000000000000001 ,
#63
b11110101101110110101110011110111 $
b00011110010111011110110001000010 %
b00000101110001000101101101011100 &
b01110101011101110100000011100010 '
b0010 (
0)
b00000000000000000000000000000000 ,
#64
0#
b01110101011101110100000011100010 $
b01111011001110111001110000111110 %
b01111110110101100001000111111010 &
b01101100111110110000011011001110 '
b0110 (
b11111010001110111010010010100011 ,
#65
1#
b10010011000001001111100100110001 $
b00010001110110110000101100101100 %
b00001100110101110101101011011001 &
b00100101110000101111100010110100 '
b0000 (
b00000000000000000000000000000000 ,
#66
0#
b00100101110000101111100010110100 $
b00110010100110100101001110001101 %
b00001100001111011001001000100111 &
b01000011000001011010011111010000 '
b00110010100110100101001110001101 ,
#67
b01000011000001011010011111010000 $
b01001111010000110011100111110111 %
b01100010011000011001110011010100 &
b01001100111010000010011011011001 '
b0111 (
b01001111010000110011100111110111 ,
#68
b01001100111010000010011011011001 $
b10101111010010011100001110101101 %
b00000000100011100000000001011000 &
b01101001000010001100000011110111 '
b0011 (
1+
b00000000000000000000000000000000 ,
#69
b01101001000010001100000011110111 $
b01101001100101101100000101001111 %
b01011110000101000011110011110101 &
b01010110110001110000110100001010 '
b0110 (
0+
b00000000000010000000000001010000 ,
#70
1#
b10101001001110001111001011110101 $
b00000111010011010010111111101011 %
b00100100001001010101010111011101 &
b01001011001111100101110000110010 '
b0111 (
b00000000000000000000000000000000 ,
#71
0#
b01001011001111100101110000110010 $
b01101111011000111011001000001111 %
b00110001111110000000111110011011 &
b01101100001101101100001101110110 '
b0110 (
#72
1#
b10010011110010010011110010001001 $
b11000101110000010100110000100101 %
b00010001111000101100110011001001 &
b00010100110110010101001011000001 '
b0101 (
1)
b00000000000000000000000000000001 ,
#73
0#
b00010100110110010101001011000001 $
b00100110101111000001111110001010 %
b01010001110000111110110010100011 &
b00011010100111011010111000011101 '
0)
b00000101001110111001111000001000 ,
#74
b00011010100111011010111000011101 $
b01101100011000011001101011000000 %
b00010000011111111101111010101001 &
b00011001011100111100000000010111 '
b0111 (
b01001011010111100100001010111110 ,
#75
b00011001011100111100000000010111 $
b00101001111100111001111011000000 %
b00110010101110000001111101111001 &
b00100110010010110001101011110001 '
b0110 (
b00000000000000000000000000000000 ,
#76
1#
b11011001101101001110010100001110 $
b00001100011011010000010010001000 %
b01110001011011011110010110010010 &
b00110010100010001010110100011000 '
b0010 (
1-
#77
0#
b00110010100010001010110100011000 $
b10100011111101101001001010101010 %
b00111011000111111111101011110001 &
b00010100111010100100100111101100 '
1+
b10001110100100100001101001101101 ,
0-
#78
b00010100111010100100100111101100 $
b01010000000010100100010011011101 %
b01001110000100110101010111010101 &
b00010101011110000100101001000101 '
b0011 (
0+
b11000100111000000000010100001110 ,
#79
b00010101011110000100101001000101 $
b01100011100010111010000000011010 %
b00101110110010001111111101000011 &
b01110011100011001000011100111010 '
b0010 (
b00000100000100000100000001000101 ,
#80
b01110011100011001000011100111010 $
b10100010010101011000011001111101 %
b00110001010100011100101100101010 &
b00010111101100011101110100010111 '
b0100 (
1+
b11010001001101110000000010111100 ,
#81
b00010111101100011101110100010111 $
b01001001000000111010100001000001 %
b01001100100011000111100011110000 &
b01001001101010011110110010110010 '
b0110 (
0+
b00110111111100011101111100111111 ,
#82
1#
b10110110010101100001001101001101 $
b00000010111000101000110000111110 %
b01011101011111000010111110000110 &
b01011011100011001011100101111011 '
b0101 (
b00000000000000000000000000000000 ,
1-
#83
0#
b01011011100011001011100101111011 $
b10111001000010001110100100000001 %
b01111000101100001000100100100011 &
b00101101010100001010011000011111 '
b0110 (
1+
b00000110111100001001011011111101 ,
0-
#84
1#
b11010010101011110101100111100000 $
b01001011010111111110001100000100 %
b00001001010111000010001110100011 &
b00111101110100001000010011001000 '
b0011 (
0+
b00000000000000000000000000000000 ,
#85
0#
b00111101110100001000010011001000 $
b01000111001011001010100001101011 %
b00000111000000101100010011110001 &
b01110000100010001010010001000010 '
b00001001010100000000000010000000 ,
#86
b01110000100010001010010001000010 $
b01110111100010110110100100110011 %
b00101010011011000101111011110011 &
b01100001111101101000100111010100 '
b0100 (
b00000000000000001000010001000000 ,
#87
b01100001111101101000100111010100 $
b10001100011000101110100011000111 %
b00010000110110111010000011000101 &
b00011101000101101000010011000101 '
1+
b01101011111111101101111111110111 ,
#88
b00011101000101101000010011000101 $
b00101101111100100010010110001010 %
b01000100001100110000100101110000 &
b01101011001010011101101010011010 '
b0000 (
0+
b00011101110111111010010011000101 ,
#89
b01101011001010011101101010011010 $
b10101111010111001110010000001010 %
b01100000100100110011001100010010 &
b00011001111100101101100111011110 '
b0101 (
1+
b10101111010111001110010000001010 ,
#90
b00011001111100101101100111011110 $
b01111010100001100000110011110000 %
b01010011101110100110100110111110 &
b01001011010001001010010100001000 '
b0000 (
0+
b01111001011000011110101011001100 ,
#91
b01001011010001001010010100001000 $
b10011110111111110000111011000110 %
b00010010000111111111110010011100 &
b00010111110100010001110111111001 '
b0111 (
1+
b10011110111111110000111011000110 ,
#92
b00010111110100010001110111111001 $
b00101001111100010001101010010101 %
b00111100101111000101001011110001 &
b01110101010011010100110101111111 '
b0010 (
0+
b00000000000000000000000000000000 ,
#93
b01110101010011010100110101111111 $
b10110010000010011010000001110000 %
b01111100001100011111110000000111 &
b01101101111111011101011010100010 '
b0101 (
1+
b11000011010000111010110100001110 ,
#94
b01101101111111011101011010100010 $
b11101010001011111101001010101001 %
b01010110010001010101001100111011 &
b01110111010110011111101001000101 '
b0100 (
b00010001110011000010101010100101 ,
#95
b01110111010110011111101001000101 $
b11001101100111110100110110000000 %
b01001001110011000110101010000110 &
b01111110010111001011111100110110 '
b0101 (
b01110111010111011111101101111111 ,
#96
b01111110010111001011111100110110 $
b11001000001010010010100110111100 %
b01100011100111101001110011000010 &
b00101000110010010001111000101001 '
b0111 (
b00110111100100001101010110110000 ,
#97
b00101000110010010001111000101001 $
b10001100011001111011101011101011 %
b00101111111110010111110000010110 &
b00111001101001001011111011101110 '
b0011 (
b00000000000000000000000000000000 ,
#98
b00111001101001001011111011101110 $
b01101001100111100011101100000100 %
b00010001001111101010010101010110 &
b01111101110101111100100001011110 '
b0000 (
0+
b00101001101000000011110000000110 ,
#99
b01111101110101111100100001011110 $
b10001111000101100110110110110100 %
b00000111111111000001100011011100 &
b01011110011010101111101101110000 '
b0011 (
1+
b10001111000101100110110110110100 ,
#100
b01011110011010101111101101110000 $
b01100110011001110001010001001100 %
b01110010010001100001001110011100 &
b00110010001001010110010100101110 '
b0001 (
0+
b00000110011010000001100001010000 ,
#101
1#
b11001101110110101001101011010001 $
b01000000001000001010111001101110 %
b01110100010000011110101101110011 &
b01000100010001010110000111001011 '
b01000000001000001010111001101110 ,
1-
#102
b10111011101110101001111000110100 $
b00101111111111001000100110101000 %
b00111111111001111010111111111101 &
b00000001000000011011010010111100 '
b0010 (
b00101111111111001000100110101000 ,
0-
#103
0#
b00000001000000011011010010111100 $
b01000000111010010110010010111001 %
b01100111000110100010111000000011 &
b01111101001100111011000011000100 '
b0001 (
b11000000000110000101000000000010 ,
#104
1#
b10000010110011000100111100111011 $
b11101001111001100111110100111111 %
b00111011100111010101001000100111 &
b01010011011110010000001111111111 '
b0100 (
1)
b11101001111001100111110100111111 ,
#105
0#
b01010011011110010000001111111111 $
b10001111000101100101011000100110 %
b01001101111100001111101100010100 &
b00011101010001010110111010000101 '
b0001 (
0)
1+
b01111011111111010101001111111111 ,
#106
1#
b11100010101110101001000101111010 $
b00110000101010111000110010001111 %
b01010000110011010100100001000011 &
b00000000111001000000101101000111 '
b0000 (
0+
b00110000101010111000110010001111 ,
1-
#107
0#
b00000000111001000000101101000111 $
b01010001101100010101001110001010 %
b00110101101000000001111101000110 &
b00110000110111011000011101011101 '
b0001 (
b01010001101100010101001110001010 ,
0-
#108
1#
b11001111001000100111100010100010 $
b00000100110000101001011111101001 %
b00110111100010010111101100001111 &
b01000010000111000010110010110011 '
b0000 (
b00000100110000101001011111101001 ,
1-
#109
0#
b01000010000111000010110010110011 $
b01111001101001011010011111000010 %
b00100100100111001011000101110010 &
b01001010000110000100010110001111 '
b0110 (
b01111001101001011010011111000010 ,
0-
#110
1#
b10110101111001111011101001110000 $
b11011010100001000110101111100011 %
b00101011101000101100000110110011 &
b00111100010111100101100100101011 '
b0111 (
1)
b00000000000000000000000000000001 ,
#111
0#
b00111100010111100101100100101011 $
b01101000000000010001101011011110 %
b01111101111011010111011011111100 &
b00110000101000000100010010011111 '
b0101 (
0)
b00000000000000000000000000000000 ,
#112
b00110000101000000100010010011111 $
b10101110100011011011101110011011 %
b01101000000010010100101000111111 &
b01110000100001111111010010011100 '
b0000 (
1+
b01001101010011010011001001100011 ,
#113
b01110000100001111111010010011100 $
b11011000100100010011111011011011 %
b01000111011100100110101100000000 &
b01010111101000100010001010011111 '
b0101 (
b11011000100100010011111011011011 ,
#114
b01010111101000100010001010011111 $
b10011111000101001000110110011111 %
b00010100110110010110001001100100 &
b00010011001111110111010011000111 '
b0001 (
b00010000110100000100100110011111 ,
#115
1#
b11101100110000001000101100111000 $
b00000001100110011110110110011101 %
b01011001100110100101010000001110 &
b01100001001100000110111111011011 '
b0000 (
0+
b00000001100110011110110110011101 ,
1-
#116
0#
b01100001001100000110111111011011 $
b10111010110010101100001111101001 %
b00011100101110000000010011101110 &
b00110001111111011011100000011111 '
b0101 (
1+
b10111010110010101100001111101001 ,
0-
#117
b00110001111111011011100000011111 $
b01001110101101011011110100001101 %
b00001000100111101101001111110111 &
b01100111100111011101011101100101 '
b0100 (
0+
b00101101010001011011110011110001 ,
#118
b01100111100111011101011101100101 $
b01110000001111001010101101011100 %
b00101110001010100110000111101111 &
b00011111001001110101001001110100 '
b0001 (
b01101111100111111101011111110111 ,
#119
1#
b11100000110110001010110110001011 $
b00001111000000110000111101111011 %
b01010001100011011011100001000110 &
b01000011110001000000001111100110 '
b0100 (
b00001111000000110000111101111011 ,
1-
#120
0#
b01000011110001000000001111100110 $
b10010101010100011011110000101100 %
b01010011010111000000101000001101 &
b01101111011001101100010110011001 '
1+
b01010011110011011011101111100110 ,
0-
#121
b01101111011001101100010110011001 $
b11000010110000101100111110100110 %
b00000111010011111100000100000010 &
b01101101010101000011110010010110 '
b0111 (
b01111111011111101100111110011101 ,
#122
b01101101010101000011110010010110 $
b01110100101000111111110110011000 %
b01111111100010001101100111000011 &
b01010101010111011000011011010101 '
b0110 (
0+
b00000000000000000000000000000000 ,
#123
1#
b10101010101000100111100100101010 $
b00101010001010110101001011101110 %
b01111000110000111010011101000000 &
b00011100110011111111000111010101 '
b0011 (
1-
#124
0#
b00011100110011111111000111010101 $
b10010101100100111001100100010101 %
b01101111001100100010010110000001 &
b00110001101010010101010000111010 '
b0010 (
1+
b00011000110000111010000101000000 ,
0-
#125
b00110001101010010101010000111010 $
b10100000110110110111100110111011 %
b00111001000110011010011111000001 &
b00001011010000111010100001001000 '
b0001 (
b10010000110011011101101001111110 ,
#126
1#
b11110100101111000101011110110111 $
b00101101110101011111111101111001 %
b00100000010001101001100010000110 &
b00100111111110111010110100110110 '
b0101 (
0+
b00101101110101011111111101111001 ,
1-
#127
0#
b00100111111110111010110100110110 $
b01001000010000100100010110111100 %
b00001000010101111001010010010010 &
b00110000100110101000000100101101 '
b0100 (
b00000111101111010011010110110000 ,
0-
#128
b00110000100110101000000100101101 $
b00111000111100100001010110111111 %
b00100001010001100001011111111011 &
b01011110110001001110001100011101 '
b0001 (
b00111000110111111001010110111111 ,
#129
1#
b10100001001110110001110011100010 $
b11000010100000010011010011011110 %
b01111100010100001100100000010111 &
b00110000010100101001101101100011 '
b0110 (
1)
b11000010100000010011010011011110 ,
1-
#130
b11001111101011010110010010011100 $
b01001011111111100010110010110100 %
b00100001011100111011110111000011 &
b00000011101011101010010101110000 '
b0100 (
0)
b00000000000000000000000000000000 ,
0-
#131
0#
b00000011101011101010010101110000 $
b00100101001000100110001100110011 %
b00000010111101010000110010011011 &
b00001010111111100110011001110010 '
b0110 (
b00100011111111111011110111110011 ,
#132
1#
b11110101000000011001100110001101 $
b11110111111101101010011000101001 %
b00010101000101101010000000010001 &
b00001010100001110100000000110101 '
b0100 (
1)
b00000000000000000000000000000001 ,
1-
#133
0#
b00001010100001110100000000110101 $
b00011111100111011110000001000110 %
b00010111110000000010100000100100 &
b00000011010010101110011101110101 '
b0001 (
0)
b00011111100101111110000000110101 ,
0-
#134
1#
b11111100101101010001100010001010 $
b00010100011101010100000010101111 %
b01110010000010111101001011010111 &
b01110010011111010000110011110110 '
b0110 (
b00010100011101010100000010101111 ,
1-
#135
b10001101100000101111001100001001 $
b11111111100011101100010111100001 %
b01011111100101101111001001010000 &
b00101011100101101011010010110111 '
b0000 (
1)
b00000000000000000000000000000001 ,
0-
#136
0#
b00101011100101101011010010110111 $
b10001011001011011010011100000111 %
b00101110010100101000000110100101 &
b01001011110111010100110100111101 '
0)
1+
b10001011001011011010011100000111 ,
#137
b01001011110111010100110100111101 $
b01111010001011111100111011100010 %
b00101111000010111100100100011001 &
b01010100001101001110000111001111 '
b0110 (
0+
b01111010001011111100111011100010 ,
#138
1#
b10101011110010110001111000110000 $
b11011010110101101110011101001010 %
b00010111011000101110011111110011 &
b01110101011110101111100111001010 '
b0100 (
1)
b00000000000000000000000000000001 ,
#139
0#
b01110101011110101111100111001010 $
b10001100110111011110000110111101 %
b00011110111000010101100101000001 &
b01110001110010111100000111100010 '
b0001 (
0)
1+
b01110111011110101111111111111011 ,
#140
1#
b10001110001101000011111000011101 $
b10101101000101011001011101011111 %
b01101010001000111100111001110101 &
b00010011001111110111111110100101 '
b0100 (
1)
0+
b10101101000101011001011101011111 ,
#141
0#
b00010011001111110111111110100101 $
b01111101011000110100111000011010 %
b00100100110011010000100101000011 &
b00010110001101001000110001000000 '
0)
b01111011001111111111111111110101 ,
#142
b00010110001101001000110001000000 $
b00111011000000011001010110000011 %
b01001100110010101000000010100111 &
b00101011010010110010110001010010 '
b0110 (
b00110110111111011000110101000011 ,
#143
1#
b11010100101101001101001110101101 $
b00100001011111110101010001010101 %
b01001010001001010111111011100000 &
b01000011000010110101010001110110 '
b0100 (
b00000000000000000000000000000000 ,
1-
#144
0#
b01000011000010110101010001110110 $
b10001101001100001101001101010110 %
b01100100010100000110111011101111 &
b00110101000101110010011101001101 '
b0001 (
1+
b01001011001011110111111011110110 ,
0-
#145
1#
b11001010111010001101100010110010 $
b00101111001110010100011110100010 %
b00110000001001001011001100110111 &
b00010100101011100001100110011110 '
b0000 (
0+
b00101111001110010100011110100010 ,
#146
0#
b00010100101011100001100110011110 $
b01000100110100101100110011010101 %
b00000111001111001001111111001000 &
b01000011000000001001101101000011 '
b0111 (
b01000100110100101100110011010101 ,
#147
b01000011000000001001101101000011 $
b01001010001111010011101100001011 %
b00000110010100000011100110001110 &
b01110010000011000110010001011101 '
b0101 (
b00000000000000000000000000000000 ,
#148
b01110010000011000110010001011101 $
b01111000010111001001110111101011 %
b00110101111111100101010010000010 &
b00001001011011110100110001010000 '
b0100 (
b01110100010111000101110111010011 ,
#149
b00001001011011110100110001010000 $
b00111111011011011010000011010010 %
b01000100011100010101001010010011 &
b00101000010100001010010110010001 '
b0111 (
b00111101111111110101110011010010 ,
#150
b00101000010100001010010110010001 $
b01101100110000011111100000100100 %
b00000011001101101110110000000111 &
b00010010011101000111010000000110 '
b0001 (
b00000000000000000000000000000000 ,
#151
1#
b11101101100010111000101111111001 $
b11110000110000100111100000000001 %
b01000101101010110010101011101011 &
b00110111010000010111110101001010 '
b0110 (
1)
b11110000110000100111100000000001 ,
1-
#152
b11001000101111101000001010110101 $
b00001110011010011010110110100001 %
b00010011000111011101000001000010 &
b00000100000010111111110111110001 '
b0111 (
0)
b00000000000000000000000000000000 ,
0-
#153
0#
b00000100000010111111110111110001 $
b00010111001010011100111000110011 %
b01101011000101111011010111001110 &
b01001110001100010111110011010010 '
b0001 (
#154
1#
b10110001110011101000001100101101 $
b00011100111001100011100011111100 %
b01000110010111001000001011001111 &
b00110010100000011110101111000001 '
b0111 (
b00011100111001100011100011111100 ,
#155
0#
b00110010100000011110101111000001 $
b01111000110111100110111010010000 %
b00010100000111100101110011000111 &
b01100010101001101001111011111000 '
b0101 (
b00000000000000000000000000000000 ,
