alu/vsrc/Adder.v
module Adder #(parameter LEN)
(
  input [LEN - 1:0] A
  input [LEN - 1:0] B
  input cin
  output [LEN - 1:0] out, 
  output cout
);

  assign {cout, out} = A + B + cin;

endmodule

alu/vsrc/alu.v
module ALU #(parameter LEN = 32)
(
  input [LEN - 1:0] A,
  input [LEN - 1:0] B,
  input [3:0] op,
  output Carry,
  output Zero,
  output Overflow,
  output reg [LEN - 1:0] Result
);

  wire cin, cout;
  wire [LEN - 1: 0] in_A, in_B, out;


  // when A-B or compare A & B, do A sub B
  assign cin = (~op[3] & ~op[2] & ~op[1] & op[0]) | (~op[3] & op[2] & op[1] & ~op[0]);
  assign in_A = A;
  assign in_B = {LEN{cin}} ^ B;
  Adder #(LEN) adder(.A(in_A), .B(in_B), .cin(cin), .out(out), .cout(cout));

  assign Carry = cout ^ cin;
  assign Zero = ~(|out);
  assign Overflow = ~(in_A[LEN - 1] ^ in_B[LEN - 1]) & (out[LEN - 1] ^ in_A[LEN - 1]);

  always @(*) begin
    case (op)
      4'b0000: Result = out;
      4'b0001: Result = out;
      4'b0010: Result = ~A;
      4'b0011: Result = A & B;
      4'b0100: Result = A | B;
      4'b0101: Result = A ^ B;
      4'b0110: Result = {{LEN - 1{1'b0}}, out[LEN-1]};
      4'b0111: Result = {31'b0, Zero};
      default: Result = 32'b0;
    endcase
  end

endmodule

alu/waveform.vcd
$version Generated by VerilatedVcd $end
$timescale 1ps $end

 $scope module TOP $end
  $var wire 32 & A [31:0] $end
  $var wire 32 ' B [31:0] $end
  $var wire  1 ) Carry $end
  $var wire  1 + Overflow $end
  $var wire 32 , Result [31:0] $end
  $var wire  1 * Zero $end
  $var wire  4 ( op [3:0] $end
  $scope module ALU $end
   $var wire 32 & A [31:0] $end
   $var wire 32 ' B [31:0] $end
   $var wire  1 ) Carry $end
   $var wire 32 . LEN [31:0] $end
   $var wire  1 + Overflow $end
   $var wire 32 , Result [31:0] $end
   $var wire  1 * Zero $end
   $var wire  1 # cin $end
   $var wire  1 - cout $end
   $var wire 32 & in_A [31:0] $end
   $var wire 32 $ in_B [31:0] $end
   $var wire  4 ( op [3:0] $end
   $var wire 32 % out [31:0] $end
   $scope module adder $end
    $var wire 32 & A [31:0] $end
    $var wire 32 $ B [31:0] $end
    $var wire 32 . LEN [31:0] $end
    $var wire  1 # cin $end
    $var wire  1 - cout $end
    $var wire 32 % out [31:0] $end
   $upscope $end
  $upscope $end
 $upscope $end
$enddefinitions $end


#0
0#
b00000000000000000000000000000000 $
b00000000000000000000000000000000 %
b01110111110111000001111111010011 &
b01011000000110000111000001011110 '
b0111 (
0)
1*
0+
b00000000000000000000000000000000 ,
0-
b00000000000000000000000000100000 .
#1
b01011000000110000111000001011110 $
b11001111111101001001000000110001 %
b00100011111001000011011001000011 &
b01111111000011100000111010101100 '
b0100 (
0*
1+
#2
b01111111000011100000111010101100 $
b10100010111100100100010011101111 %
b00011100010011011011110110100010 &
b00101111001001110100100001110100 '
b0111 (
b01111111111011100011111011101111 ,
#3
b00101111001001110100100001110100 $
b01001011011101010000011000010110 %
b00110011011011010000110010111110 &
b01011010100011111101111010001011 '
b0011 (
0+
b00000000000000000000000000000000 ,
#4
b01011010100011111101111010001011 $
b10001101111111001110101101001001 %
b01000100111000010101110010101111 &
b01101111001011010111101101001011 '
b0111 (
1+
b00010010000011010000110010001010 ,
#5
b01101111001011010111101101001011 $
b10110100000011101101011111111010 %
b01100001000010101111111001010101 &
b00000000011101001011100101000001 '
b0000 (
b00000000000000000000000000000000 ,
#6
b00000000011101001011100101000001 $
b01100001011111111011011110010110 %
b00011011010011001000011000100000 &
b01110100000110101111000001100110 '
b0101 (
0+
b01100001011111111011011110010110 ,
#7
b01110100000110101111000001100110 $
b10001111011001110111011010000110 %
b00110001001010101110011111000001 &
b01010100100001110101001110101111 '
b0100 (
1+
b01101111010101100111011001000110 ,
#8
b01010100100001110101001110101111 $
b10000101101100100011101101110000 %
b01111111010101111001011001011011 &
b00010100001001110110111000010110 '
b0010 (
b01110101101011111111011111101111 ,
#9
b00010100001001110110111000010110 $
b10010011011111110000010001110001 %
b01011010100100001001100111011110 &
b00100010010100111110101110101100 '
b0110 (
b10000000101010000110100110100100 ,
#10
1#
b11011101101011000001010001010011 $
b00111000001111001010111000110010 %
b01000111101011101101010111001101 &
b00011010001100000000101101111111 '
b0100 (
0+
b00000000000000000000000000000000 ,
1-
#11
0#
b00011010001100000000101101111111 $
b01100001110111101110000101001100 %
b01011111110010101000100100100001 &
b00111110000101000100000111000010 '
b0011 (
b01011111101111101101111111111111 ,
0-
#12
b00111110000101000100000111000010 $
b10011101110111101100101011100011 %
b01011001000101110001101010111001 &
b01011010011000011111111101100100 '
b0111 (
1+
b00011110000000000000000100000000 ,
#13
b01011010011000011111111101100100 $
b10110011011110010001101000011101 %
b00010101000101010001011101010100 &
b00001101110011110000110000100010 '
b0011 (
b00000000000000000000000000000000 ,
#14
b00001101110011110000110000100010 $
b00100010111001000010001101110110 %
b00011001111111101010110000000100 &
b01010010101100000110100011010010 '
b0110 (
0+
b00000101000001010000010000000000 ,
#15
1#
b10101101010011111001011100101101 $
b11000111010011100100001100110010 %
b01101110110010101010011110000100 &
b00110011101110110110011100100111 '
b0010 (
1)
b00000000000000000000000000000001 ,
1-
#16
0#
b00110011101110110110011100100111 $
b10100010100001100000111010101011 %
b00000101000000110011001000001001 &
b01001111000001111110110101000111 '
b0011 (
0)
1+
b10010001001101010101100001111011 ,
0-
#17
b01001111000001111110110101000111 $
b01010100000010110001111101010000 %
b00011011101110000101001101010101 &
b00000000001100101101010100001001 '
b0001 (
0+
b00000101000000110010000000000001 ,
#18
1#
b11111111110011010010101011110110 $
b00011011100001010111111001001100 %
b00101000110110011110110001001000 &
b01111111100010100110101101100100 '
b0000 (
b00011011100001010111111001001100 ,
1-
#19
0#
b01111111100010100110101101100100 $
b10101000011001000101011110101100 %
b00110011101110000000101000001110 &
b01011010000110110000010101000010 '
b0110 (
1+
b10101000011001000101011110101100 ,
0-
#20
1#
b10100101111001001111101010111101 $
b11011001100111010000010011001100 %
b00001111110000100001100011001010 &
b00100001110010011101101100010000 '
b0010 (
1)
0+
b00000000000000000000000000000001 ,
#21
0#
b00100001110010011101101100010000 $
b00110001100010111111001111011010 %
b01000011111001001001011111100101 &
b00000001100101000110010000110001 '
b0001 (
0)
b11110000001111011110011100110101 ,
#22
1#
b11111110011010111001101111001110 $
b01000010010100000011001110110100 %
b01110111000101010010010110101100 &
b01011010101010110111111011101010 '
b0100 (
b01000010010100000011001110110100 ,
1-
#23
0#
b01011010101010110111111011101010 $
b11010001110000001010010010010110 %
b01011001011011001111101111101000 &
b01101111110000001001011000111111 '
b0000 (
1+
b01111111101111110111111111101110 ,
0-
#24
b01101111110000001001011000111111 $
b11001001001011011001001000100111 %
b00010110010101001011000010101110 &
b00001001101111110100001001000011 '
b0011 (
b11001001001011011001001000100111 ,
#25
b00001001101111110100001001000011 $
b00100000000100111111001011110001 %
b01000010011010011110000011000000 &
b01111000100010011110100111000111 '
b0101 (
0+
b00000000000101000000000000000010 ,
#26
b01111000100010011110100111000111 $
b10111010111100111100101010000111 %
b01101110111100111100101000010011 &
b01111101100011010001101111010001 '
b0100 (
1+
b00111010111000000000100100000111 ,
#27
b01111101100011010001101111010001 $
b11101100100000001110010111100100 %
b00001111100110001010001111001100 &
b00011001010001010110111100100110 '
b0011 (
b01111111111111111101101111010011 ,
#28
b00011001010001010110111100100110 $
b00101000110111100001001011110010 %
b00000100110001001101000100110101 &
b01000010000111110101101101101110 '
b0100 (
0+
b00001001000000000010001100000100 ,
#29
b01000010000111110101101101101110 $
b01000110111001000010110010100011 %
b00001110000110000110110010110011 &
b01110101110101110110010101111100 '
b0001 (
b01000110110111111101101101111111 ,
#30
1#
b10001010001010001001101010000011 $
b10011000010000010000011100110111 %
b00111001101111111111001111011110 &
b00000101100110010111111001000111 '
b0011 (
1)
b10011000010000010000011100110111 ,
#31
0#
b00000101100110010111111001000111 $
b00111111010110010111001000100101 %
b01111111100101111000011010000111 &
b01001001011111100001011000101100 '
0)
b00000001100110010111001001000110 ,
#32
b01001001011111100001011000101100 $
b11001001000101011001110010110011 %
b00000011100000110101101011110011 &
b01000000100100110011101111011001 '
b0101 (
1+
b01001001000101100000011000000100 ,
#33
b01000000100100110011101111011001 $
b01000100000101101001011011001100 %
b01100001110100010010111011000100 &
b00011010000000000011011111000001 '
b0111 (
0+
b01000011000100000110000100101010 ,
#34
b00011010000000000011011111000001 $
b01111011110100010110011010000101 %
b01001101111011100000111010110111 &
b00110000010101001110100001101111 '
b0110 (
b00000000000000000000000000000000 ,
#35
1#
b11001111101010110001011110010000 $
b00011101100110010010011001001000 %
b00001100101110110101011101111100 &
b01110010101111101100100100110000 '
b0001 (
#36
b10001101010000010011011011001111 $
b10011001111111001000111001001100 %
b01111111010001000000011101101000 &
b01100001101100101001001101000011 '
1)
b10011001111111001000111001001100 ,
1-
#37
b10011110010011010110110010111100 $
b00011101100100010111010000100101 %
b01000000110101001010010010011011 &
b01110001010010110011011100010000 '
b0010 (
0)
b00011101100100010111010000100101 ,
0-
#38
0#
b01110001010010110011011100010000 $
b10110010000111111101101110101011 %
b00000010100110000001011011011000 &
b01110110000100000000100001000101 '
b0000 (
1+
b10111111001010110101101101100100 ,
#39
b01110110000100000000100001000101 $
b01111000101010000001111100011101 %
b01000011111001011111010001111001 &
b00000100001010000111010011111000 '
b0111 (
0+
b01111000101010000001111100011101 ,
#40
b00000100001010000111010011111000 $
b01001000000011100110100101110001 %
b01011111010011101101011101011100 &
b00111101111010000110100011010110 '
b0011 (
b00000000000000000000000000000000 ,
#41
b00111101111010000110100011010110 $
b10011101001101110100000000110010 %
b00011100100000011001010101010000 &
b00111101011111111110111101011110 '
b0010 (
1+
b00011101010010000100000001010100 ,
#42
b00111101011111111110111101011110 $
b01011010000000011000010010101110 %
b01011011010010001011011101110101 &
b01000001000000110100101001010001 '
b0111 (
0+
b11100011011111100110101010101111 ,
#43
b01000001000000110100101001010001 $
b10011100010011000000000111000110 %
b01110100101110110101100010000100 &
b00100010110101000111100100010101 '
b0000 (
1+
b00000000000000000000000000000000 ,
#44
b00100010110101000111100100010101 $
b10010111100011111101000110011001 %
b01111101111011101000111111010011 &
b01110000110000101000011111001100 '
b0001 (
b10010111100011111101000110011001 ,
#45
1#
b10001111001111010111100000110011 $
b00001101001011000000100000000111 %
b00010000111000010000100101100100 &
b01111101011111011101111101001000 '
b0000 (
0+
b00001101001011000000100000000111 ,
#46
0#
b01111101011111011101111101001000 $
b10001110010111101110100010101100 %
b00011100010111010110110010111101 &
b01111100110000011110011010110000 '
1+
b10001110010111101110100010101100 ,
#47
b01111100110000011110011010110000 $
b10011001000111110101001101101101 %
b00100101011001101110101111100111 &
b00111101100101101000101101001100 '
b0100 (
b10011001000111110101001101101101 ,
#48
b00111101100101101000101101001100 $
b01100010111111010111011100110011 %
b01000111101101011101101000111000 &
b01000000001011101010001000100100 '
0+
b00111101111101101110101111101111 ,
#49
b01000000001011101010001000100100 $
b10000111111001000111110001011100 %
b00101100001001000010001111110111 &
b00000100000101001001011010011101 '
b0001 (
1+
b01000111101111111111101000111100 ,
#50
1#
b11111011111010110110100101100010 $
b00101000000011111000110101011010 %
b00000110011010011101001100110010 &
b01100011011000110110110111111001 '
0+
b00101000000011111000110101011010 ,
1-
#51
b10011100100111001001001000000110 $
b10100011000001100110010100111001 %
b01100110010010010000000010110101 &
b01111111111001010000001101001001 '
b0000 (
1)
b10100011000001100110010100111001 ,
#52
0#
b01111111111001010000001101001001 $
b11100110001011100000001111111110 %
b00001111101001100100010001100100 &
b01011011001011011011101010111110 '
b0110 (
0)
1+
b11100110001011100000001111111110 ,
0-
#53
1#
b10100100110100100100010101000001 $
b10110100011110001000100110100110 %
b01111001100101101100001111101100 &
b01001111111010010001001101000011 '
b0111 (
1)
0+
b00000000000000000000000000000001 ,
1-
#54
0#
b01001111111010010001001101000011 $
b11001001011111111101011100101111 %
b01111101100001110111101100110101 &
b01001101110101111010001100010110 '
b0101 (
0)
1+
b00000000000000000000000000000000 ,
0-
#55
b01001101110101111010001100010110 $
b11001011010111110001111001001011 %
b00110001110011010001101011101101 &
b01011110101110001010110001111010 '
b0001 (
b00110000010100001101100000100011 ,
#56
1#
b10100001010001110101001110000101 $
b11010011000101000110111001110011 %
b01011000110100011000001111010110 &
b01111011000101100001100100111000 '
b0010 (
1)
0+
b11010011000101000110111001110011 ,
#57
0#
b01111011000101100001100100111000 $
b11010011111001111001110100001110 %
b01100001100010001000000000000010 &
b00100000011111010000010100011111 '
0)
1+
b10100111001011100111110000101001 ,
#58
b00100000011111010000010100011111 $
b10000010000001011000010100100001 %
b01011011100010101011001100111110 &
b01101000001100101101111101010111 '
b0110 (
b10011110011101110111111111111101 ,
#59
1#
b10010111110011010010000010101000 $
b11110011010101111101001111100111 %
b01001011100111001110111010111111 &
b00010100010101110000001101001110 '
b0010 (
1)
0+
b00000000000000000000000000000001 ,
#60
0#
b00010100010101110000001101001110 $
b01011111111100111111001000001101 %
b00111111110101111001111100111000 &
b00011010110000001101011010000001 '
b0111 (
0)
b10110100011000110001000101000000 ,
#61
b00011010110000001101011010000001 $
b01011010100110000111010110111001 %
b01110001111110101011100010001000 &
b00000001000010011101011100110110 '
b0001 (
b00000000000000000000000000000000 ,
#62
1#
b11111110111101100010100011001001 $
b01110000111100001110000101010010 %
b01100001100111011100000100110110 &
b00010000101100000001101110011010 '
b0010 (
b01110000111100001110000101010010 ,
1-
#63
0#
b00010000101100000001101110011010 $
b01110010010011011101110011010000 %
b00010010010001000001010000110110 &
b00001010010001101101111110000110 '
b0001 (
b10011110011000100011111011001001 ,
0-
#64
1#
b11110101101110010010000001111001 $
b00000111111111010011010010110000 %
b01100101101111101110000001001011 &
b00000111110011100101101010111011 '
b0100 (
b00000111111111010011010010110000 ,
1-
#65
0#
b00000111110011100101101010111011 $
b01101101100011010011101100000110 %
b00101001111111000011010000101100 &
b00111001100110110111010110101000 '
b0010 (
b01100111111111101111101011111011 ,
0-
#66
b00111001100110110111010110101000 $
b01100011100101111010100111010100 %
b01101011101101110110011101010110 &
b00010010011011001111100101111110 '
b0100 (
b11010110000000111100101111010011 ,
#67
b00010010011011001111100101111110 $
b01111110001001000110000011010100 %
b00101010001101001000000100110001 &
b01110011111101010111100110000000 '
b01111011111111111111111101111110 ,
#68
b01110011111101010111100110000000 $
b10011110001010011111101010110001 %
b00100110010010000010011001010111 &
b01001111100000000010110010111110 '
1+
b01111011111101011111100110110001 ,
#69
b01001111100000000010110010111110 $
b01110101110010000101001100010101 %
b01100010100010100110110110100010 &
b00011011000111010001101101111101 '
b0011 (
0+
b01101111110010000010111011111111 ,
#70
b00011011000111010001101101111101 $
b01111101101001111000100100011111 %
b00100010111000010100101110001001 &
b01011010111101001011101010110110 '
b0010 (
b00000010000010000000100100100000 ,
#71
b01011010111101001011101010110110 $
b01111101110101100000011000111111 %
b01000110100110111001011101101010 &
b01001100111011110111001100111110 '
b0011 (
b11011101000111101011010001110110 ,
#72
b01001100111011110111001100111110 $
b10010011100010110000101010101000 %
b01101010001110101110011010010101 &
b00101110100011010011010001110101 '
b0001 (
1+
b01000100100010110001001100101010 ,
#73
1#
b11010001011100101100101110001010 $
b00111011101011011011001000100000 %
b01101001000001111111000001111110 &
b01000000110100010100100010101011 '
b0011 (
0+
b00111011101011011011001000100000 ,
1-
#74
0#
b01000000110100010100100010101011 $
b10101001110110010011100100101001 %
b00110111101111100000110110101010 &
b00100110100100000010100011110110 '
b0001 (
1+
b01000000000000010100000000101010 ,
0-
#75
1#
b11011001011011111101011100001001 $
b00010001001011011110010010110100 %
b01010100010010111100110111101100 &
b01010000100011000101110100100010 '
b0100 (
0+
b00010001001011011110010010110100 ,
1-
#76
0#
b01010000100011000101110100100010 $
b10100100110110000010101100001110 %
b01001111100100100011101010101000 &
b00111100010000111100010001111001 '
1+
b01010100110011111101110111101110 ,
0-
#77
b00111100010000111100010001111001 $
b10001011110101011111111100100001 %
b01000101111011101100000010011101 &
b01100110011110000100010110101010 '
b0011 (
b01111111110100111111111011111001 ,
#78
b01100110011110000100010110101010 $
b10101100011001110000011001000111 %
b01011100110010000100101110110001 &
b00001100110000000110110000000001 '
b01000100011010000100000010001000 ,
#79
b00001100110000000110110000000001 $
b01101001100010001011011110110010 %
b01011011110101001011011000011100 &
b01101111010010101101100110100011 '
b0010 (
0+
b00001100110000000100100000000001 ,
#80
b01101111010010101101100110100011 $
b11001011000111111000111110111111 %
b01101111001110000010001111010110 &
b00010010001011000010010100101101 '
b0111 (
1+
b10100100001010110100100111100011 ,
#81
b00010010001011000010010100101101 $
b10000001011001000100100100000011 %
b00011101010111000110100000010001 &
b01011000110001111011110010010111 '
b0101 (
b00000000000000000000000000000000 ,
#82
b01011000110001111011110010010111 $
b01110110001001000010010010101000 %
b01001100100010101000001110000010 &
b01000011000000101010001100101100 '
b0100 (
0+
b01000101100110111101010010000110 ,
#83
b01000011000000101010001100101100 $
b10001111100011010010011010101110 %
b00001100011010001011101010001101 &
b00101100000010101001001110101010 '
b0001 (
1+
b01001111100010101010001110101110 ,
#84
1#
b11010011111101010110110001010101 $
b11100000010111100010011011100011 %
b01010110100011011101000100011110 &
b01100011110010001010000101010100 '
b0100 (
1)
0+
b11100000010111100010011011100011 ,
1-
#85
0#
b01100011110010001010000101010100 $
b10111010010101100111001001110010 %
b00101000100000010100001001101010 &
b00111000000101000110111101000000 '
b0010 (
0)
1+
b01110111110011011111000101011110 ,
0-
#86
b00111000000101000110111101000000 $
b01100000100101011011000110101010 %
b00110100000100000010100101011111 &
b00000111101001101010100111101001 '
b0100 (
0+
b11010111011111101011110110010101 ,
#87
b00000111101001101010100111101001 $
b00111011101101101101001101001000 %
b01010010000011000000100111010010 &
b01001101100101010110101010000110 '
b0101 (
b00110111101101101010100111111111 ,
#88
b01001101100101010110101010000110 $
b10011111101000010111010001011000 %
b01100011111111010110001111000101 &
b00101010010111011011011000110111 '
b0111 (
1+
b00011111100110010110001101010100 ,
#89
b00101010010111011011011000110111 $
b10001110010110110001100111111100 %
b01000101011011101110101001110111 &
b00000110001100100110110001010011 '
b0001 (
b00000000000000000000000000000000 ,
#90
1#
b11111001110011011001001110101100 $
b00111111001111000111111000100100 %
b01000001111111011000110010100111 &
b01110101011010101001000000101010 '
b0100 (
0+
b00111111001111000111111000100100 ,
1-
#91
0#
b01110101011010101001000000101010 $
b10110111011010000001110011010001 %
b00011001100000001110100110001100 &
b00010010110001101111100000111011 '
b0001 (
1+
b01110101111111111001110010101111 ,
0-
#92
1#
b11101101001110010000011111000100 $
b00000110101110011111000101010001 %
b00111101111100111011100110110000 &
b01011111010100010111101110111110 '
0+
b00000110101110011111000101010001 ,
1-
#93
b10100000101011101000010001000001 $
b11011110101000100011110111110010 %
b00010000111100111011111001001001 &
b01101011101110100011011001001011 '
b0101 (
1)
b11011110101000100011110111110010 ,
0-
#94
0#
b01101011101110100011011001001011 $
b01111100101011011111010010010100 %
b00100100110001010000101110001101 &
b01000010010010000000011101101010 '
b0000 (
0)
b01111011010010011000100000000010 ,
#95
b01000010010010000000011101101010 $
b01100111000011010001001011110111 %
b01011111001001101000000111000111 &
b01101010110010010100100111010100 '
b0100 (
b01100111000011010001001011110111 ,
#96
b01101010110010010100100111010100 $
b11001001111011111100101110011011 %
b01101010000101000101010100100100 &
b00011110110110010111001100110011 '
b0101 (
1+
b01111111111011111100100111010111 ,
#97
b00011110110110010111001100110011 $
b10001000111011011100100001010111 %
b00110001010001011110110011111001 &
b01110000111001010111110100000101 '
b0110 (
b01110100110011010010011000010111 ,
#98
1#
b10001111000110101000001011111010 $
b11000000011000000110111111110100 %
b01011110111011111100101001111001 &
b01010100111000101110000011001011 '
b0100 (
1)
0+
b00000000000000000000000000000001 ,
#99
0#
b01010100111000101110000011001011 $
b10110011110100101010101101000100 %
b00011001010110100001001111111010 &
b00011010010100011100101101000010 '
b0011 (
0)
1+
b01011110111011111110101011111011 ,
#100
b00011010010100011100101101000010 $
b00110011101010111101111100111100 %
b01000011000011110011011100011110 &
b01011100010011110101011111101001 '
b0110 (
0+
b00011000010100000000001101000010 ,
#101
1#
b10100011101100001010100000010110 $
b11100110101111111101111100110101 %
b01111110111100000111111101110000 &
b01110101110100000100000101110110 '
b0000 (
1)
b00000000000000000000000000000001 ,
1-
#102
0#
b01110101110100000100000101110110 $
b11110100110000001100000011100110 %
b00010011100110011000010001011001 &
b00110011110000111111101100100110 '
b0100 (
0)
1+
b11110100110000001100000011100110 ,
0-
#103
b00110011110000111111101100100110 $
b01000111010111010111111101111111 %
b01101011010001010010110001101110 &
b01000100101101111011100101110000 '
b0010 (
0+
b00110011110110111111111101111111 ,
#104
b01000100101101111011100101110000 $
b10101111111111001110010111011110 %
b01101110111110110110100000101110 &
b01101001011111001100010011111101 '
b0101 (
1+
b10010100101110101101001110010001 ,
#105
b01101001011111001100010011111101 $
b11011000011110000010110100101011 %
b01010110011110100100010101000011 &
b01001000101000110100011011000101 '
b0111 (
b00000111100001111010110011010011 ,
#106
b01001000101000110100011011000101 $
b10011111000111011000110000001000 %
b01110110000011011001000110011000 &
b00110010101101111001101111101001 '
b0100 (
b00000000000000000000000000000000 ,
#107
b00110010101101111001101111101001 $
b10101000110001010010110110000001 %
b00011101010001111000011111010110 &
b01100011111111011000100011100010 '
b0111 (
b01110110101111111001101111111001 ,
#108
b01100011111111011000100011100010 $
b10000001010001010001000010111000 %
b00010010000101101110100010011010 &
b01000010111011010101001101011011 '
b0101 (
b00000000000000000000000000000000 ,
#109
b01000010111011010101001101011011 $
b01010101000001000011101111110101 %
b00110001010000111111111110010101 &
b01011100010001110110011101010101 '
b0000 (
0+
b01010000111110111011101111000001 ,
#110
b01011100010001110110011101010101 $
b10001101100010110110011011101010 %
b01010110101000111000001011100011 &
b00011111010101101001111001110100 '
b0010 (
1+
b10001101100010110110011011101010 ,
#111
b00011111010101101001111001110100 $
b01110101111110100010000101010111 %
b01110001011011011001011001011100 &
b00011110010001110001110111100100 '
b0100 (
0+
b10101001010111000111110100011100 ,
#112
b00011110010001110001110111100100 $
b10001111101101001011010001000000 %
b00011110111111101010001000010000 &
b00110001111000001010001000111101 '
b0010 (
1+
b01111111011011111001111111111100 ,
#113
b00110001111000001010001000111101 $
b01010000110111110100010001001101 %
b00101011111000010010100110000010 &
b00011101001001011100111010101011 '
b0000 (
0+
b11100001000000010101110111101111 ,
#114
b00011101001001011100111010101011 $
b01001001000001101111100000101101 %
b00100100011111011110011100111111 &
b00001100001000010011011011011010 '
b01001001000001101111100000101101 ,
#115
b00001100001000010011011011011010 $
b00110000100111110001111000011001 %
b01011111011000101010110001100111 &
b01100010100110110111110000011101 '
b0110 (
b00110000100111110001111000011001 ,
#116
1#
b10011101011001001000001111100010 $
b11111100110001110011000001001010 %
b00000101000100001011101101100011 &
b01011000101010010000110110110101 '
b0011 (
1)
b00000000000000000000000000000001 ,
#117
0#
b01011000101010010000110110110101 $
b01011101101110011100100100011000 %
b01001001100110000011110110010010 &
b01110101111100001001010110001011 '
b0100 (
0)
b00000000000000000000100100100001 ,
#118
b01110101111100001001010110001011 $
b10111111100010001101001100011101 %
b01111111000001010011110011000111 &
b00001000000001110111111000100101 '
b0110 (
1+
b01111101111110001011110110011011 ,
#119
1#
b11110111111110001000000111011010 $
b01110110111111011011111010100010 %
b00001001010101010001110011000111 &
b00111001010010110111110110111010 '
b0010 (
0+
b00000000000000000000000000000000 ,
1-
#120
0#
b00111001010010110111110110111010 $
b01000010101000001001101010000001 %
b00101101111101101100100000001010 &
b00001111111011110000000010011101 '
b0111 (
b11110110101010101110001100111000 ,
0-
#121
b00001111111011110000000010011101 $
b00111101111001011100100010100111 %
b00101110111001111100101100110110 &
b00000001010111001001011011111001 '
b0011 (
b00000000000000000000000000000000 ,
#122
b00000001010111001001011011111001 $
b00110000010001000110001000101111 %
b00100101101010010000111111011000 &
b00100000010110110011100100001001 '
b0111 (
b00000000010001001000001000110000 ,
#123
b00100000010110110011100100001001 $
b01000110000001000100100011100001 %
b01010000001011100100111110100000 &
b01001100001111000110001010001011 '
b0100 (
b00000000000000000000000000000000 ,
#124
b01001100001111000110001010001011 $
b10011100011010101011001000101011 %
b00111111011010110100100011011001 &
b01110000101110100100100111001011 '
b0000 (
1+
b01011100001111100110111110101011 ,
#125
b01110000101110100100100111001011 $
b10110000001001011001001010100100 %
b00011000001001010000011100001111 &
b01010000000111001111011000110010 '
b0010 (
b10110000001001011001001010100100 ,
#126
b01010000000111001111011000110010 $
b01101000010000011111110101000001 %
b00111001100000100000110000001010 &
b01010101001011011011000110010101 '
b0111 (
0+
b11100111110110101111100011110000 ,
#127
b01010101001011011011000110010101 $
b10001110101011111011110110011111 %
b00001101100101101010110011101110 &
b00011110110001011110111100100111 '
b0100 (
1+
b00000000000000000000000000000000 ,
#128
b00011110110001011110111100100111 $
b00101100010111001001110000010101 %
b01000101101010001101011010110100 &
b00011101110010110010101111101111 '
b0111 (
0+
b00011111110101111110111111101111 ,
#129
b00011101110010110010101111101111 $
b01100011011101000000001010100011 %
b01000000101010000101001111010110 &
b00100111001000000100100010110110 '
b0100 (
b00000000000000000000000000000000 ,
#130
b00100111001000000100100010110110 $
b01100111110010001001110010001100 %
b00010111111011110011100001001110 &
b01010101000101110001000011000000 '
b0110 (
b01100111101010000101101111110110 ,
#131
1#
b10101010111010001110111100111111 $
b11000010110110000010011110001110 %
b00001110100011001011101100111001 &
b00000011111111101101101111110110 '
b0011 (
1)
b00000000000000000000000000000001 ,
#132
0#
b00000011111111101101101111110110 $
b00010010100010111001011100101111 %
b00100011011100010101110000001001 &
b00101001101001111110101111001110 '
b0101 (
0)
b00000010100011001001101100110000 ,
#133
b00101001101001111110101111001110 $
b01001101000110010100011111010111 %
b01101010001101101001111100010101 &
b01111001110101100011101101101111 '
b0110 (
b00001010110101101011011111000111 ,
#134
1#
b10000110001010011100010010010000 $
b11110000011000000110001110100110 %
b01001110001000011011000011001101 &
b00111001010000011000010001001000 '
b0010 (
1)
b00000000000000000000000000000001 ,
#135
0#
b00111001010000011000010001001000 $
b10000111011000110011010100010101 %
b00111110001011011111100101011111 &
b01010001011001101000101101010111 '
b0101 (
0)
1+
b10110001110111100100111100110010 ,
#136
b01010001011001101000101101010111 $
b10001111100101001000010010110110 %
b00010000110101011011111000001110 &
b00001010111010001001011101100001 '
b0111 (
b01101111010010110111001000001000 ,
#137
b00001010111010001001011101100001 $
b00011011101111100101010101101111 %
b00111100001001101001000001110010 &
b00011000011111110100010001001111 '
b0100 (
0+
b00000000000000000000000000000000 ,
#138
b00011000011111110100010001001111 $
b01010100101001011101010011000001 %
b01011101011001111111100001100001 &
b01011110001010000001101100000011 '
b0011 (
b00111100011111111101010001111111 ,
#139
b01011110001010000001101100000011 $
b10111011100100000001001101100100 %
b00000110101100001101111001110101 &
b00011110110100000110111011011010 '
b0010 (
1+
b01011100001000000001100000000001 ,
#140
b00011110110100000110111011011010 $
b00100101100000010100110101001111 %
b01101001010001010100001001000011 &
b00110110101111111010011100101000 '
b0001 (
0+
b11111001010011110010000110001010 ,
#141
1#
b11001001010000000101100011010111 $
b00110010100001011001101100011011 %
b01011011110010001010011010101111 &
b01000101010011000110001001100001 '
b00110010100001011001101100011011 ,
1-
#142
b10111010101100111001110110011110 $
b00010110011111000100010001001110 %
b01001111101010001010001000010100 &
b01101000101111011011111001101010 '
b0000 (
b00010110011111000100010001001110 ,
#143
0#
b01101000101111011011111001101010 $
b10111000011001100110000001111110 %
b01100011111000111101011010000010 &
b01010010111101000101110110000000 '
b0110 (
1+
b10111000011001100110000001111110 ,
0-
#144
1#
b10101101000010111010001001111111 $
b00010000111011110111100100000010 %
b01000100010110110110110101111100 &
b00100001000101100000111001001101 '
b0101 (
0+
b00000000000000000000000000000000 ,
#145
0#
b00100001000101100000111001001101 $
b01100101011100010111101111001001 %
b00010101100011010100111001000001 &
b01011111010001000000011110101101 '
b01100101010011010110001100110001 ,
#146
b01011111010001000000011110101101 $
b01110100110100010101010111101110 %
b00110110110111000010010100111000 &
b01110000000110011100010110111011 '
b0100 (
b01001010110010010100100111101100 ,
#147
b01110000000110011100010110111011 $
b10100110111101011110101011110011 %
b00101101010110001010110111000100 &
b00101100010000000101011000101110 '
b0101 (
1+
b01110110110111011110010110111011 ,
#148
b00101100010000000101011000101110 $
b01011001100110010000001111110010 %
b01000010100110110010010101111000 &
b00001001101010000100111010001111 '
b0100 (
0+
b00000001000110001111101111101010 ,
#149
b00001001101010000100111010001111 $
b01001100010000110111010000000111 %
b01110101101010001100100100011010 &
b00010000010110010010110100000101 '
b0000 (
b01001011101110110110111111111111 ,
#150
b00010000010110010010110100000101 $
b10000110000000011111011000011111 %
b01001111110101101011010101110011 &
b01111001100111100110111101001000 '
b0010 (
1+
b10000110000000011111011000011111 ,
#151
b01111001100111100110111101001000 $
b11001001011101010010010010111011 %
b01111111000110111011001010001101 &
b01010101011001110001010111110111 '
b10110000001010010100101010001100 ,
#152
b01010101011001110001010111110111 $
b11010100100000101100100010000100 %
b00110010010111111000101110011101 &
b00100101000011111011100000001011 '
b0011 (
b10000000111001000100110101110010 ,
#153
b00100101000011111011100000001011 $
b01010111011011110100001110101000 %
b00001111010010110101000001111011 &
b00001000111100111000111010001110 '
b0110 (
0+
b00100000000011111000100000001001 ,
#154
1#
b11110111000011000111000101110001 $
b00000110010101111100000111101101 %
b01100110000011010101000011001001 &
b01001101010011101111110000001010 '
b00000000000000000000000000000000 ,
1-
